Metadata-Version: 1.0
Name: eziod
Version: 0.0.3
Summary: a easy image object dataset
Home-page: https://github.com/alexw994/eziod
Author: alexwww94
Author-email: 243114328@qq.com
License: MIT Licence
Keywords: pip,eziod
Platform: any
